git_flush/__init__.py
git_flush/main.py
git_flush-0.1.4.dist-info/LICENSE
git_flush-0.1.4.dist-info/METADATA
git_flush-0.1.4.dist-info/WHEEL
git_flush-0.1.4.dist-info/entry_points.txt
git_flush-0.1.4.dist-info/RECORD
