Metadata-Version: 2.1
Name: git-flush
Version: 0.1.4
Summary: 
Author: Nathan Patton
Author-email: npatton@gmail.com
Requires-Python: >=3.9,<4.0
Classifier: Programming Language :: Python :: 3
Classifier: Programming Language :: Python :: 3.9
Classifier: Programming Language :: Python :: 3.10
Classifier: Programming Language :: Python :: 3.11
Classifier: Programming Language :: Python :: 3.12
Requires-Dist: gitpython (>=3.1.41,<4.0.0)
Requires-Dist: typer[all] (>=0.9.0,<0.10.0)
